srinathpdf/__init__.py
srinathpdf/pdf2image.py
srinathpdf/pdf2text.py
srinathpdf-2.3.dist-info/licenses/LICENSE
srinathpdf-2.3.dist-info/METADATA
srinathpdf-2.3.dist-info/WHEEL
srinathpdf-2.3.dist-info/top_level.txt
srinathpdf-2.3.dist-info/RECORD
